<?xml version="1.0" encoding="utf-8" ?><dwsync><file name="styles.css" server="karlnieb.com/karlnieb.com/" local="3321944604" remote="11931527972" /><file name="5thbase.html" server="karlnieb.com/karlnieb.com/" local="3322227328" remote="11931527492" /><file name="fluency.html" server="karlnieb.com/karlnieb.com/" local="3326269339" remote="11931527792" /><file name="getitboard.html" server="karlnieb.com/karlnieb.com/" local="3321945841" remote="11931527792" /><file name="index.html" server="karlnieb.com/karlnieb.com/" local="3334015579" remote="11931527852" /><file name="karl.jpg" server="karlnieb.com/karlnieb.com/" local="3321875188" remote="11931527852" /><file name="livewell.html" server="karlnieb.com/karlnieb.com/" local="3326269285" remote="11931527852" /><file name="trestle.html" server="karlnieb.com/karlnieb.com/" local="3322228132" remote="11931527972" /><file name="shareflect.html" server="karlnieb.com/karlnieb.com/" local="3326269225" remote="11931527972" /><file name="blink.html" server="karlnieb.com/karlnieb.com/" local="3324902627" remote="11931527492" /><file name="magicmeal.html" server="karlnieb.com/karlnieb.com/" local="3326272134" remote="11931527852" /><file name="mealmaker.html" server="karlnieb.com/karlnieb.com/" local="3326271795" remote="11931527852" /></dwsync>